subprocess_loop/__init__.py
subprocess_loop/child.py
subprocess_loop-1.0.9.dist-info/LICENSE
subprocess_loop-1.0.9.dist-info/METADATA
subprocess_loop-1.0.9.dist-info/WHEEL
subprocess_loop-1.0.9.dist-info/top_level.txt
subprocess_loop-1.0.9.dist-info/RECORD
