Metadata-Version: 2.1
Name: subprocess_loop
Version: 1.0.9
Summary: subprocess exchange with stdio
Home-page: https://github.com/maxavaiable/py-subprocess-loop
Author: dev mx
Requires-Python: >=3.0
License-File: LICENSE
